nearkpss/__init__.py
nearkpss/critical_values.py
nearkpss/long_run_variance.py
nearkpss/mkpss.py
nearkpss/utils.py
nearkpss-1.0.0.dist-info/LICENSE
nearkpss-1.0.0.dist-info/METADATA
nearkpss-1.0.0.dist-info/WHEEL
nearkpss-1.0.0.dist-info/top_level.txt
nearkpss-1.0.0.dist-info/RECORD
