Metadata-Version: 2.1
Name: nearkpss
Version: 1.0.0
Summary: Modified KPSS Tests for Near Integration - Harris, Leybourne, and McCabe (2007)
Author-email: Dr Merwan Roudane <merwanroudane920@gmail.com>
Maintainer-email: Dr Merwan Roudane <merwanroudane920@gmail.com>
License: MIT
Project-URL: Homepage, https://github.com/merwanroudane/modifiedkpss
Project-URL: Documentation, https://github.com/merwanroudane/modifiedkpss#readme
Project-URL: Repository, https://github.com/merwanroudane/modifiedkpss
Project-URL: Issues, https://github.com/merwanroudane/modifiedkpss/issues
Keywords: econometrics,time series,unit root,KPSS test,near integration,stationarity,cointegration,hypothesis testing
Classifier: Development Status :: 5 - Production/Stable
Classifier: Intended Audience :: Science/Research
Classifier: Intended Audience :: Education
Classifier: License :: OSI Approved :: MIT License
Classifier: Operating System :: OS Independent
Classifier: Programming Language :: Python :: 3
Classifier: Programming Language :: Python :: 3.8
Classifier: Programming Language :: Python :: 3.9
Classifier: Programming Language :: Python :: 3.10
Classifier: Programming Language :: Python :: 3.11
Classifier: Programming Language :: Python :: 3.12
Classifier: Topic :: Scientific/Engineering :: Mathematics
Classifier: Topic :: Scientific/Engineering :: Information Analysis
Requires-Python: >=3.8
License-File: LICENSE
Requires-Dist: numpy>=1.20.0
Provides-Extra: all
Requires-Dist: nearkpss[dev,docs]; extra == "all"
Requires-Dist: scipy>=1.7.0; extra == "all"
Requires-Dist: pandas>=1.3.0; extra == "all"
Requires-Dist: matplotlib>=3.5.0; extra == "all"
Provides-Extra: dev
Requires-Dist: pytest>=7.0.0; extra == "dev"
Requires-Dist: pytest-cov>=4.0.0; extra == "dev"
Provides-Extra: docs
Requires-Dist: sphinx>=5.0.0; extra == "docs"
Requires-Dist: sphinx-rtd-theme>=1.0.0; extra == "docs"
Requires-Dist: numpydoc>=1.5.0; extra == "docs"
